plons/AccrDisk.py
plons/ArchimedianSpiral.py
plons/CMF_meanRho.py
plons/ConversionFactors_cgs.py
plons/GeometricalFunctions.py
plons/LoadData.py
plons/OrbitalEvolution.py
plons/OrbitalEvolutionWAql.py
plons/PhysicalQuantities.py
plons/Plotting.py
plons/Profiles1D.py
plons/RadialStructurePlots1D.py
plons/RhoRradialFit.py
plons/SlicePlots2D.py
plons/SmoothingKernelScript.py
plons/TerminalVelocity.py
plons/Tools.py
plons/Tubes.py
plons/__init__.py
plons/plot3D.py
plons/readPhantomDump.py
plons-0.0.28.dist-info/licenses/LICENSE
plons-0.0.28.dist-info/METADATA
plons-0.0.28.dist-info/WHEEL
plons-0.0.28.dist-info/top_level.txt
plons-0.0.28.dist-info/RECORD
