Metadata-Version: 2.4
Name: plons
Version: 0.0.28
Summary: PLOtting tool for Nice Simulations
Author-email: Jolien Malfait <jolien.malfait@kuleuven.be>, Mats Esseldeurs <mats.esseldeurs@kuleuven.be>
License:                     GNU GENERAL PUBLIC LICENSE
Project-URL: Homepage, https://github.com/Ensor-code/plons
Keywords: SPH,Phantom,Astrophysics,Astronomy
Classifier: License :: OSI Approved :: GNU General Public License v3 (GPLv3)
Classifier: Programming Language :: Python
Classifier: Programming Language :: Python :: 3
Classifier: Topic :: Scientific/Engineering :: Physics
Classifier: Topic :: Scientific/Engineering :: Astronomy
Classifier: Topic :: Scientific/Engineering :: Visualization
Requires-Python: >=3.7
License-File: LICENSE
Requires-Dist: matplotlib
Requires-Dist: healpy
Requires-Dist: scipy
Requires-Dist: numpy>=1.17
Requires-Dist: numba
Requires-Dist: sarracen
Provides-Extra: dev
Requires-Dist: black; extra == "dev"
Requires-Dist: bumpver; extra == "dev"
Requires-Dist: pip-tools; extra == "dev"
Requires-Dist: pytest; extra == "dev"
Dynamic: license-file
